diffeomorphic/__init__.py
diffeomorphic/_version.py
diffeomorphic/cli.py
diffeomorphic/diffeomorphic.py
diffeomorphic/diffeomorphic_movie.py
diffeomorphic/diffeomorphic_movie_warpshift.py
diffeomorphic/utils.py
diffeomorphic-0.1.0.dist-info/LICENSE
diffeomorphic-0.1.0.dist-info/METADATA
diffeomorphic-0.1.0.dist-info/WHEEL
diffeomorphic-0.1.0.dist-info/entry_points.txt
diffeomorphic-0.1.0.dist-info/top_level.txt
diffeomorphic-0.1.0.dist-info/RECORD
