Metadata-Version: 2.1
Name: diffeomorphic
Version: 0.1.0
Summary: Diffeomorphic transformations for image and video morphing in psychological experiments
Home-page: https://github.com/AhsanKhodami/diffeomorphic
Author: Mohammad Ahsan Khodami
Author-email: Mohammad Ahsan Khodami <ahsan.khodami@gmail.com>
License: MIT
Classifier: Programming Language :: Python :: 3
Classifier: License :: OSI Approved :: MIT License
Classifier: Operating System :: OS Independent
Requires-Python: >=3.6
License-File: LICENSE
Requires-Dist: numpy
Requires-Dist: matplotlib
Requires-Dist: pillow
Requires-Dist: scipy
Requires-Dist: opencv-python
